mac/mac_controlpath.v
/* 
Developed by : Vecha Sathwik
Date : 17/01/2025
Version : Beta
Rev : 1.0
Status : Working
Updates : Synchronous flow of data without pipeline
*/
`timescale 1ns / 1ps
module mac_controlpath (
    input clk,
    input rst,
    input go,
    input cmp,
    output reg load_a,
    output reg load_b,
    output reg load_m,
    output reg load_acc,
    output reg load_out,
    output reg count_enable,
    output reg done
);

//States
parameter S0 = 3'b000;
parameter S1 = 3'b001;
parameter S2 = 3'b010;
parameter S3 = 3'b011;
parameter S4 = 3'b100;
parameter S5 = 3'b101;
parameter S6 = 3'b110;
parameter S7 = 3'b111;

//Internal Signals
reg [2:0] present_state;
reg [2:0] next_state;

//For reset Logic and Present State Logic
always @(posedge rst or posedge clk) begin
    if(rst == 1'b1) begin
        present_state = S0;
        done = 1'b0;
    end
    else begin
        present_state = next_state;
    end
end

//MAC Control Logic
always @(go or present_state) begin
    if(go == 1'b1 & present_state == S0) begin
        load_a = 1'b0;
        load_b = 1'b0;
        load_m = 1'b0;
        load_acc = 1'b0;
        load_out = 1'b0;
        count_enable = 1'b0;
        next_state = S1;
    end
    else begin
        case (present_state)
            S1 : begin
                load_a = 1'b1;
                load_b = 1'b1;
                load_m = 1'b0;
                load_acc = 1'b0;
                load_out = 1'b0;
                count_enable = 1'b1;
                next_state = S2;
            end

            S2 : begin
                load_a = 1'b0;
                load_b = 1'b0;
                load_m = 1'b0;
                load_acc = 1'b0;
                load_out = 1'b0;
                count_enable = 1'b0;
                next_state = S3;
            end

            S3 : begin
                load_a = 1'b0;
                load_b = 1'b0;
                load_m = 1'b1;
                load_acc = 1'b0;
                count_enable = 1'b0;
                load_out = 1'b0;
                next_state = S4;
            end

            S4 : begin
                load_a = 1'b0;
                load_b = 1'b0;
                load_m = 1'b0;
                load_acc = 1'b0;
                load_out = 1'b0;
                count_enable = 1'b0;
                next_state = S5;
            end

            S5 : begin
                load_a = 1'b0;
                load_b = 1'b0;
                load_m = 1'b0;
                load_acc = 1'b1;
                load_out = 1'b0;
                count_enable = 1'b0;
                next_state = S6;
            end

            S6 : begin
                load_a = 1'b0;
                load_b = 1'b0;
                load_m = 1'b0;
                load_acc = 1'b0;
                load_out = 1'b0;
                count_enable = 1'b0;
                next_state = (cmp == 1'b1) ? S7 : S1;
            end
            S7 : begin
                load_out = 1'b1;
                next_state = S0;
                done = 1'b1;
            end

            default : next_state = S0; 
        endcase
    end
end

endmodule

mac/mac_datapath.v
/* 
Developed by : Vecha Sathwik
Date : 17/01/2025
Version : Beta
Rev : 1.0
Status : Working
Updates : Synchronous flow of data without pipeline
*/

`timescale 1ns / 1ps
module mac_datapath (
    input clk,
    input rst,
    input [3:0] A,
    input [3:0] B,
    input load_a,
    input load_b,
    input load_m,
    input load_acc,
    input load_out,
    input count_enable,
    output reg [11:0] out,
    output reg cmp
    //output reg done
);

//Internal Signals
reg [11:0] Racc;
reg reset_flag;
reg [11:0] temp_min;
reg [11:0] temp_mout;
reg [3:0] count_out;

//For reset Logic
always @(posedge rst or posedge clk) begin
    if(rst == 1'b1) begin
        Racc <= 12'b0;
        //done <= 1'b0;
        out <= 12'b0;
        count_out <= 4'b0;
    end
    else begin
        if(load_out == 1'b1) begin
            out <= Racc;
            //done <= 1'b1;
        end
        else if (load_a == 1'b1 & load_b == 1'b1) begin
            temp_min <= A*B;            
        end
        else if(load_m == 1'b1) begin
            temp_mout <= temp_min;
        end
        else if(load_acc == 1'b1) begin
            Racc <= Racc + temp_mout;
        end
    end
end


//Logic for counter
//The below logic may not be triggered for clock instead we can provide count_enable in process sensitivity list
always @(posedge(clk)) begin
    if(count_enable == 1'b1 & count_out <= 4'b1010) begin
        count_out <= count_out + 4'b0001;
        cmp <= 1'b0;
    end
    else if(count_out == 4'b1010) begin
        cmp <= 1'b1;
    end
end


endmodule

mac/mac_topmodule.v
/* 
Developed by : Vecha Sathwik
Date : 17/01/2025
Version : Beta
Rev : 1.0
Status : Working
Updates : Synchronous flow of data without pipeline
*/
`include "mac_controlpath.v"
`include "mac_datapath.v"
`timescale 1ns / 1ps
module mac_topmodule (
    input clk,
    input rst,
    input [3:0] A,
    input [3:0] B,
    input go,
    output [11:0] out,
    output done
);

//Internal Signals
wire load_a;
wire load_b;
wire load_m;
wire load_acc;
wire load_out;
wire cmp;
wire count_enable;

//Instantiate the datapath and controlpath
mac_datapath datapath_inst1(
    .rst(rst),
    .clk(clk),
    .A(A),
    .B(B),
    .load_a(load_a),
    .load_b(load_b),
    .load_m(load_m),
    .load_acc(load_acc),
    .load_out(load_out),
    .count_enable(count_enable),
    .out(out),
    .cmp(cmp)
);

mac_controlpath controlpath_inst1(
    .clk(clk),
    .rst(rst),
    .go(go),
    .cmp(cmp),
    .load_a(load_a),
    .load_b(load_b),
    .load_m(load_m),
    .load_acc(load_acc),
    .load_out(load_out),
    .count_enable(count_enable),
    .done(done)
);
    
endmodule

mac/mac_testbench_class.v
/* 
Developed by : Vecha Sathwik
Date : 17/01/2025
Version : Beta
Rev : 1.0
Status : Working
Updates : Synchronous flow of data without pipeline
*/
`include "mac_topmodule.v"
`timescale 1ns / 1ps
module mac_testbench;

//Input Signals
reg clk;
reg rst;
reg go;
reg [3:0] data_in1;
reg [3:0] data_in2;
wire [11:0] out;
//wire done;

//Instantiate the mac_topmodule
mac_topmodule mac_topmodule_inst1(
    .clk(clk),
    .rst(rst),
    .A(data_in1),
    .B(data_in2),
    .go(go),
    .out(out),
    .done(done)
);

//Internal Variable
integer i;

//Clock Generation
initial begin
    clk = 1'b0;
    forever begin
        #5 clk = ~clk;
    end
end

//Stimuli
initial begin
    $dumpfile("dump.vcd");
    $dumpvars;
   data_in1=12;
    data_in2=6;
    go=0;
    rst=1;
    #50; 
    rst=0;

    #50;
    go=1; 
    #35; 
    go=0;

    $display("Applying Test Values:");
    for (i = 0; i < 10; i = i + 1) begin
        data_in1 = i; // Generating values (e.g., 0, 5, 10, 15, ...)
        data_in2 = 2*i+1;
        #76;  // Wait for 10 time units
     
    end
    #1000;
    $finish;
end


    



    
endmodule

mac/dump.vcd
$date
	Thu Jan 23 12:03:16 2025
$end
$version
	Icarus Verilog
$end
$timescale
	1ps
$end
$scope module mac_testbench $end
$var wire 12 ! out [11:0] $end
$var wire 1 " done $end
$var reg 1 # clk $end
$var reg 4 $ data_in1 [3:0] $end
$var reg 4 % data_in2 [3:0] $end
$var reg 1 & go $end
$var reg 1 ' rst $end
$var integer 32 ( i [31:0] $end
$scope module mac_topmodule_inst1 $end
$var wire 4 ) A [3:0] $end
$var wire 4 * B [3:0] $end
$var wire 1 # clk $end
$var wire 1 & go $end
$var wire 1 ' rst $end
$var wire 12 + out [11:0] $end
$var wire 1 , load_out $end
$var wire 1 - load_m $end
$var wire 1 . load_b $end
$var wire 1 / load_acc $end
$var wire 1 0 load_a $end
$var wire 1 " done $end
$var wire 1 1 count_enable $end
$var wire 1 2 cmp $end
$scope module controlpath_inst1 $end
$var wire 1 # clk $end
$var wire 1 & go $end
$var wire 1 ' rst $end
$var wire 1 2 cmp $end
$var parameter 3 3 S0 $end
$var parameter 3 4 S1 $end
$var parameter 3 5 S2 $end
$var parameter 3 6 S3 $end
$var parameter 3 7 S4 $end
$var parameter 3 8 S5 $end
$var parameter 3 9 S6 $end
$var parameter 3 : S7 $end
$var reg 1 1 count_enable $end
$var reg 1 " done $end
$var reg 1 0 load_a $end
$var reg 1 / load_acc $end
$var reg 1 . load_b $end
$var reg 1 - load_m $end
$var reg 1 , load_out $end
$var reg 3 ; next_state [2:0] $end
$var reg 3 < present_state [2:0] $end
$upscope $end
$scope module datapath_inst1 $end
$var wire 4 = A [3:0] $end
$var wire 4 > B [3:0] $end
$var wire 1 # clk $end
$var wire 1 1 count_enable $end
$var wire 1 0 load_a $end
$var wire 1 / load_acc $end
$var wire 1 . load_b $end
$var wire 1 - load_m $end
$var wire 1 , load_out $end
$var wire 1 ' rst $end
$var reg 12 ? Racc [11:0] $end
$var reg 1 2 cmp $end
$var reg 4 @ count_out [3:0] $end
$var reg 12 A out [11:0] $end
$var reg 12 B temp_min [11:0] $end
$var reg 12 C temp_mout [11:0] $end
$upscope $end
$upscope $end
$upscope $end
$enddefinitions $end
$comment Show the parameter values. $end
$dumpall
b111 :
b110 9
b101 8
b100 7
b11 6
b10 5
b1 4
b0 3
$end
#0
$dumpvars
bx C
bx B
b0 A
b0 @
b0 ?
b110 >
b1100 =
b0 <
b0 ;
x2
x1
x0
x/
x.
x-
x,
b0 +
b110 *
b1100 )
bx (
1'
0&
b110 %
b1100 $
0#
0"
b0 !
$end
#5000
1#
#10000
0#
#15000
1#
#20000
0#
#25000
1#
#30000
0#
#35000
1#
#40000
0#
#45000
1#
#50000
0#
0'
#55000
1#
#60000
0#
#65000
1#
#70000
0#
#75000
1#
#80000
0#
#85000
1#
#90000
0#
#95000
1#
#100000
b1 ;
01
0,
0/
0-
0.
00
0#
1&
#105000
b10 ;
11
1.
10
b1 <
1#
#110000
0#
#115000
b1001000 B
02
b1 @
b11 ;
01
0.
00
b10 <
1#
#120000
0#
#125000
b100 ;
1-
b11 <
1#
#130000
0#
#135000
b1001000 C
b101 ;
0-
b100 <
1#
b1 %
b1 *
b1 >
b0 $
b0 )
b0 =
b0 (
0&
#140000
0#
#145000
b110 ;
1/
b101 <
1#
#150000
0#
#155000
b1001000 ?
b1 ;
0/
b110 <
1#
#160000
0#
#165000
b10 ;
11
1.
10
b1 <
1#
#170000
0#
#175000
b0 B
b10 @
b11 ;
01
0.
00
b10 <
1#
#180000
0#
#185000
b100 ;
1-
b11 <
1#
#190000
0#
#195000
b0 C
b101 ;
0-
b100 <
1#
#200000
0#
#205000
b110 ;
1/
b101 <
1#
#210000
0#
#211000
b11 %
b11 *
b11 >
b1 $
b1 )
b1 =
b1 (
#215000
b1 ;
0/
b110 <
1#
#220000
0#
#225000
b10 ;
11
1.
10
b1 <
1#
#230000
0#
#235000
b11 B
b11 @
b11 ;
01
0.
00
b10 <
1#
#240000
0#
#245000
b100 ;
1-
b11 <
1#
#250000
0#
#255000
b11 C
b101 ;
0-
b100 <
1#
#260000
0#
#265000
b110 ;
1/
b101 <
1#
#270000
0#
#275000
b1001011 ?
b1 ;
0/
b110 <
1#
#280000
0#
#285000
b10 ;
11
1.
10
b1 <
1#
#287000
b101 %
b101 *
b101 >
b10 $
b10 )
b10 =
b10 (
#290000
0#
#295000
b1010 B
b100 @
b11 ;
01
0.
00
b10 <
1#
#300000
0#
#305000
b100 ;
1-
b11 <
1#
#310000
0#
#315000
b1010 C
b101 ;
0-
b100 <
1#
#320000
0#
#325000
b110 ;
1/
b101 <
1#
#330000
0#
#335000
b1010101 ?
b1 ;
0/
b110 <
1#
#340000
0#
#345000
b10 ;
11
1.
10
b1 <
1#
#350000
0#
#355000
b101 @
b11 ;
01
0.
00
b10 <
1#
#360000
0#
#363000
b111 %
b111 *
b111 >
b11 $
b11 )
b11 =
b11 (
#365000
b100 ;
1-
b11 <
1#
#370000
0#
#375000
b101 ;
0-
b100 <
1#
#380000
0#
#385000
b110 ;
1/
b101 <
1#
#390000
0#
#395000
b1011111 ?
b1 ;
0/
b110 <
1#
#400000
0#
#405000
b10 ;
11
1.
10
b1 <
1#
#410000
0#
#415000
b10101 B
b110 @
b11 ;
01
0.
00
b10 <
1#
#420000
0#
#425000
b100 ;
1-
b11 <
1#
#430000
0#
#435000
b10101 C
b101 ;
0-
b100 <
1#
#439000
b1001 %
b1001 *
b1001 >
b100 $
b100 )
b100 =
b100 (
#440000
0#
#445000
b110 ;
1/
b101 <
1#
#450000
0#
#455000
b1110100 ?
b1 ;
0/
b110 <
1#
#460000
0#
#465000
b10 ;
11
1.
10
b1 <
1#
#470000
0#
#475000
b100100 B
b111 @
b11 ;
01
0.
00
b10 <
1#
#480000
0#
#485000
b100 ;
1-
b11 <
1#
#490000
0#
#495000
b100100 C
b101 ;
0-
b100 <
1#
#500000
0#
#505000
b110 ;
1/
b101 <
1#
#510000
0#
#515000
b10011000 ?
b1 ;
0/
b110 <
1#
b1011 %
b1011 *
b1011 >
b101 $
b101 )
b101 =
b101 (
#520000
0#
#525000
b10 ;
11
1.
10
b1 <
1#
#530000
0#
#535000
b110111 B
b1000 @
b11 ;
01
0.
00
b10 <
1#
#540000
0#
#545000
b100 ;
1-
b11 <
1#
#550000
0#
#555000
b110111 C
b101 ;
0-
b100 <
1#
#560000
0#
#565000
b110 ;
1/
b101 <
1#
#570000
0#
#575000
b11001111 ?
b1 ;
0/
b110 <
1#
#580000
0#
#585000
b10 ;
11
1.
10
b1 <
1#
#590000
0#
#591000
b1101 %
b1101 *
b1101 >
b110 $
b110 )
b110 =
b110 (
#595000
b1001110 B
b1001 @
b11 ;
01
0.
00
b10 <
1#
#600000
0#
#605000
b100 ;
1-
b11 <
1#
#610000
0#
#615000
b1001110 C
b101 ;
0-
b100 <
1#
#620000
0#
#625000
b110 ;
1/
b101 <
1#
#630000
0#
#635000
b100011101 ?
b1 ;
0/
b110 <
1#
#640000
0#
#645000
b10 ;
11
1.
10
b1 <
1#
#650000
0#
#655000
b1010 @
b11 ;
01
0.
00
b10 <
1#
#660000
0#
#665000
12
b100 ;
1-
b11 <
1#
#667000
b1111 %
b1111 *
b1111 >
b111 $
b111 )
b111 =
b111 (
#670000
0#
#675000
b101 ;
0-
b100 <
1#
#680000
0#
#685000
b110 ;
1/
b101 <
1#
#690000
0#
#695000
b101101011 ?
b111 ;
0/
b110 <
1#
#700000
0#
#705000
1"
b0 ;
1,
b111 <
1#
#710000
0#
#715000
b101101011 !
b101101011 +
b101101011 A
b0 <
1#
#720000
0#
#725000
1#
#730000
0#
#735000
1#
#740000
0#
#743000
b1 %
b1 *
b1 >
b1000 $
b1000 )
b1000 =
b1000 (
#745000
1#
#750000
0#
#755000
1#
#760000
0#
#765000
1#
#770000
0#
#775000
1#
#780000
0#
#785000
1#
#790000
0#
#795000
1#
#800000
0#
#805000
1#
#810000
0#
#815000
1#
#819000
b11 %
b11 *
b11 >
b1001 $
b1001 )
b1001 =
b1001 (
#820000
0#
#825000
1#
#830000
0#
#835000
1#
#840000
0#
#845000
1#
#850000
0#
#855000
1#
#860000
0#
#865000
1#
#870000
0#
#875000
1#
#880000
0#
#885000
1#
#890000
0#
#895000
1#
b1010 (
