mac/mac_controlpath.v
/* 
Developed by : Vecha Sathwik
Date : 17/01/2025
Version : Beta
Rev : 1.0
Status : Working
Updates : Synchronous flow of data without pipeline
*/
`timescale 1ns / 1ps
module mac_controlpath (
    input clk,
    input rst,
    input go,
    input cmp,
    output reg load_a,
    output reg load_b,
    output reg load_m,
    output reg load_acc,
    output reg load_out,
    output reg count_enable
);

//States
parameter S0 = 3'b000;
parameter S1 = 3'b001;
parameter S2 = 3'b010;
parameter S3 = 3'b011;
parameter S4 = 3'b100;
parameter S5 = 3'b101;
parameter S6 = 3'b110;
parameter S7 = 3'b111;

//Internal Signals
reg [2:0] present_state;
reg [2:0] next_state;

//For reset Logic and Present State Logic
always @(posedge rst or posedge clk) begin
    if(rst == 1'b1) begin
        present_state = S0;
    end
    else begin
        present_state = next_state;
    end
end

//MAC Control Logic
always @(go or present_state) begin
    if(go == 1'b1 & present_state == S0) begin
        load_a = 1'b0;
        load_b = 1'b0;
        load_m = 1'b0;
        load_acc = 1'b0;
        load_out = 1'b0;
        count_enable = 1'b0;
        next_state = S1;
    end
    else begin
        case (present_state)
            S1 : begin
                load_a = 1'b1;
                load_b = 1'b1;
                load_m = 1'b0;
                load_acc = 1'b0;
                load_out = 1'b0;
                count_enable = 1'b1;
                next_state = S2;
            end

            S2 : begin
                load_a = 1'b0;
                load_b = 1'b0;
                load_m = 1'b0;
                load_acc = 1'b0;
                load_out = 1'b0;
                count_enable = 1'b0;
                next_state = S3;
            end

            S3 : begin
                load_a = 1'b0;
                load_b = 1'b0;
                load_m = 1'b1;
                load_acc = 1'b0;
                count_enable = 1'b0;
                load_out = 1'b0;
                next_state = S4;
            end

            S4 : begin
                load_a = 1'b0;
                load_b = 1'b0;
                load_m = 1'b0;
                load_acc = 1'b0;
                load_out = 1'b0;
                count_enable = 1'b0;
                next_state = S5;
            end

            S5 : begin
                load_a = 1'b0;
                load_b = 1'b0;
                load_m = 1'b0;
                load_acc = 1'b1;
                load_out = 1'b0;
                count_enable = 1'b0;
                next_state = S6;
            end

            S6 : begin
                load_a = 1'b0;
                load_b = 1'b0;
                load_m = 1'b0;
                load_acc = 1'b0;
                load_out = 1'b0;
                count_enable = 1'b0;
                next_state = (cmp == 1'b1) ? S7 : S1;
            end
            S7 : begin
                load_out = 1'b1;
                next_state = S0;
            end

            default : next_state = S0; 
        endcase
    end
end

endmodule

mac/mac_datapath.v
/* 
Developed by : Vecha Sathwik
Date : 17/01/2025
Version : Beta
Rev : 1.0
Status : Working
Updates : Synchronous flow of data without pipeline
*/

`timescale 1ns / 1ps
module mac_datapath (
    input clk,
    input rst,
    input [3:0] A,
    input [3:0] B,
    input load_a,
    input load_b,
    input load_m,
    input load_acc,
    input load_out,
    input count_enable,
    output reg [11:0] out,
    output reg cmp,
    output reg done
);

//Internal Signals
reg [11:0] Racc;
reg reset_flag;
reg [7:0] temp_min;
reg [7:0] temp_mout;
reg [3:0] count_out;

//For reset Logic
always @(posedge rst or posedge clk) begin
    if(rst == 1'b1) begin
        Racc <= 12'b0;
        done <= 1'b0;
        out <= 12'b0;
        count_out <= 4'b0;
    end
    else begin
        if(load_out == 1'b1) begin
            out <= Racc;
            done <= 1'b1;
        end
        else if (load_a == 1'b1 & load_b == 1'b1) begin
            temp_min <= A*B;            
        end
        else if(load_m == 1'b1) begin
            temp_mout <= temp_min;
        end
        else if(load_acc == 1'b1) begin
            Racc <= Racc + temp_mout;
        end
    end
end


//Logic for counter
//The below logic may not be triggered for clock instead we can provide count_enable in process sensitivity list
always @(posedge(clk)) begin
    if(count_enable == 1'b1 & count_out <= 4'b1010) begin
        count_out <= count_out + 4'b0001;
        cmp <= 1'b0;
    end
    else if(count_out == 4'b1010) begin
        cmp <= 1'b1;
    end
end


endmodule

mac/mac_topmodule.v
/* 
Developed by : Vecha Sathwik
Date : 17/01/2025
Version : Beta
Rev : 1.0
Status : Working
Updates : Synchronous flow of data without pipeline
*/
`include "mac_controlpath.v"
`include "mac_datapath.v"
`timescale 1ns / 1ps
module mac_topmodule (
    input clk,
    input rst,
    input [3:0] A,
    input [3:0] B,
    input go,
    output [11:0] out,
    output done
);

//Internal Signals
wire load_a;
wire load_b;
wire load_m;
wire load_acc;
wire load_out;
wire cmp;
wire count_enable;

//Instantiate the datapath and controlpath
mac_datapath datapath_inst1(
    .rst(rst),
    .clk(clk),
    .A(A),
    .B(B),
    .load_a(load_a),
    .load_b(load_b),
    .load_m(load_m),
    .load_acc(load_acc),
    .load_out(load_out),
    .count_enable(count_enable),
    .out(out),
    .cmp(cmp),
    .done(done)
);

mac_controlpath controlpath_inst1(
    .clk(clk),
    .rst(rst),
    .go(go),
    .cmp(cmp),
    .load_a(load_a),
    .load_b(load_b),
    .load_m(load_m),
    .load_acc(load_acc),
    .load_out(load_out),
    .count_enable(count_enable)
);
    
endmodule

mac/mac_testbench.v
/* 
Developed by : Vecha Sathwik
Date : 17/01/2025
Version : Beta
Rev : 1.0
Status : Working
Updates : Synchronous flow of data without pipeline
*/
`include "mac_topmodule.v"
`timescale 1ns / 1ps
module mac_testbench;

//Input Signals
reg clk;
reg rst;
reg go;
reg [3:0] A;
reg [3:0] B;
wire [11:0] out;
wire done;

//Instantiate the mac_topmodule
mac_topmodule mac_topmodule_inst1(
    .clk(clk),
    .rst(rst),
    .A(A),
    .B(B),
    .go(go),
    .out(out),
    .done(done)
);

//Internal Variable
integer i;

//Clock Generation
initial begin
    clk = 1'b0;
    forever begin
        #5 clk = ~clk;
    end
end

//Stimuli
initial begin
    $dumpfile("mac_testbench.vcd");
    $dumpvars;
    rst = 1'b1;
    #10;
    rst = 1'b0;
    go = 1'b1;
    #7;
    go =1'b0;
    for(i=0; i<16; i=i+1) begin
        A = $random%16;
        B = $random%16;
        #25;
    end

    #1000;
    $finish;

end
    
endmodule

mac/mac_testbench.vcd
$date
	Fri Jan 17 13:56:06 2025
$end
$version
	Icarus Verilog
$end
$timescale
	1ps
$end
$scope module mac_testbench $end
$var wire 12 ! out [11:0] $end
$var wire 1 " done $end
$var reg 4 # A [3:0] $end
$var reg 4 $ B [3:0] $end
$var reg 1 % clk $end
$var reg 1 & go $end
$var reg 1 ' rst $end
$var integer 32 ( i [31:0] $end
$scope module mac_topmodule_inst1 $end
$var wire 4 ) A [3:0] $end
$var wire 4 * B [3:0] $end
$var wire 1 % clk $end
$var wire 1 & go $end
$var wire 1 ' rst $end
$var wire 12 + out [11:0] $end
$var wire 1 , load_out $end
$var wire 1 - load_m $end
$var wire 1 . load_b $end
$var wire 1 / load_acc $end
$var wire 1 0 load_a $end
$var wire 1 " done $end
$var wire 1 1 count_enable $end
$var wire 1 2 cmp $end
$scope module controlpath_inst1 $end
$var wire 1 % clk $end
$var wire 1 & go $end
$var wire 1 ' rst $end
$var wire 1 2 cmp $end
$var parameter 3 3 S0 $end
$var parameter 3 4 S1 $end
$var parameter 3 5 S2 $end
$var parameter 3 6 S3 $end
$var parameter 3 7 S4 $end
$var parameter 3 8 S5 $end
$var parameter 3 9 S6 $end
$var parameter 3 : S7 $end
$var reg 1 1 count_enable $end
$var reg 1 0 load_a $end
$var reg 1 / load_acc $end
$var reg 1 . load_b $end
$var reg 1 - load_m $end
$var reg 1 , load_out $end
$var reg 3 ; next_state [2:0] $end
$var reg 3 < present_state [2:0] $end
$upscope $end
$scope module datapath_inst1 $end
$var wire 4 = A [3:0] $end
$var wire 4 > B [3:0] $end
$var wire 1 % clk $end
$var wire 1 1 count_enable $end
$var wire 1 0 load_a $end
$var wire 1 / load_acc $end
$var wire 1 . load_b $end
$var wire 1 - load_m $end
$var wire 1 , load_out $end
$var wire 1 ' rst $end
$var reg 12 ? Racc [11:0] $end
$var reg 1 2 cmp $end
$var reg 4 @ count_out [3:0] $end
$var reg 1 " done $end
$var reg 12 A out [11:0] $end
$var reg 8 B temp_min [7:0] $end
$var reg 8 C temp_mout [7:0] $end
$upscope $end
$upscope $end
$upscope $end
$enddefinitions $end
$comment Show the parameter values. $end
$dumpall
b111 :
b110 9
b101 8
b100 7
b11 6
b10 5
b1 4
b0 3
$end
#0
$dumpvars
bx C
bx B
b0 A
b0 @
b0 ?
bx >
bx =
b0 <
b0 ;
x2
x1
x0
x/
x.
x-
x,
b0 +
bx *
bx )
bx (
1'
x&
0%
bx $
bx #
0"
b0 !
$end
#5000
1%
#10000
b1 ;
01
0,
0/
0-
0.
00
0%
1&
0'
#15000
b10 ;
11
1.
10
b1 <
1%
#17000
b1 $
b1 *
b1 >
b100 #
b100 )
b100 =
b0 (
0&
#20000
0%
#25000
b100 B
02
b1 @
b11 ;
01
0.
00
b10 <
1%
#30000
0%
#35000
b100 ;
1-
b11 <
1%
#40000
0%
#42000
b11 $
b11 *
b11 >
b1001 #
b1001 )
b1001 =
b1 (
#45000
b100 C
b101 ;
0-
b100 <
1%
#50000
0%
#55000
b110 ;
1/
b101 <
1%
#60000
0%
#65000
b100 ?
b1 ;
0/
b110 <
1%
#67000
b1101 $
b1101 *
b1101 >
b1101 #
b1101 )
b1101 =
b10 (
#70000
0%
#75000
b10 ;
11
1.
10
b1 <
1%
#80000
0%
#85000
b10101001 B
b10 @
b11 ;
01
0.
00
b10 <
1%
#90000
0%
#92000
b10 $
b10 *
b10 >
b101 #
b101 )
b101 =
b11 (
#95000
b100 ;
1-
b11 <
1%
#100000
0%
#105000
b10101001 C
b101 ;
0-
b100 <
1%
#110000
0%
#115000
b110 ;
1/
b101 <
1%
#117000
b1101 $
b1101 *
b1101 >
b1 #
b1 )
b1 =
b100 (
#120000
0%
#125000
b10101101 ?
b1 ;
0/
b110 <
1%
#130000
0%
#135000
b10 ;
11
1.
10
b1 <
1%
#140000
0%
#142000
b110 #
b110 )
b110 =
b101 (
#145000
b1001110 B
b11 @
b11 ;
01
0.
00
b10 <
1%
#150000
0%
#155000
b100 ;
1-
b11 <
1%
#160000
0%
#165000
b1001110 C
b101 ;
0-
b100 <
1%
#167000
b1100 $
b1100 *
b1100 >
b1101 #
b1101 )
b1101 =
b110 (
#170000
0%
#175000
b110 ;
1/
b101 <
1%
#180000
0%
#185000
b11111011 ?
b1 ;
0/
b110 <
1%
#190000
0%
#192000
b110 $
b110 *
b110 >
b1001 #
b1001 )
b1001 =
b111 (
#195000
b10 ;
11
1.
10
b1 <
1%
#200000
0%
#205000
b110110 B
b100 @
b11 ;
01
0.
00
b10 <
1%
#210000
0%
#215000
b100 ;
1-
b11 <
1%
#217000
b1010 $
b1010 *
b1010 >
b101 #
b101 )
b101 =
b1000 (
#220000
0%
#225000
b110110 C
b101 ;
0-
b100 <
1%
#230000
0%
#235000
b110 ;
1/
b101 <
1%
#240000
0%
#242000
b111 $
b111 *
b111 >
b1001 (
#245000
b100110001 ?
b1 ;
0/
b110 <
1%
#250000
0%
#255000
b10 ;
11
1.
10
b1 <
1%
#260000
0%
#265000
b100011 B
b101 @
b11 ;
01
0.
00
b10 <
1%
#267000
b1111 $
b1111 *
b1111 >
b10 #
b10 )
b10 =
b1010 (
#270000
0%
#275000
b100 ;
1-
b11 <
1%
#280000
0%
#285000
b100011 C
b101 ;
0-
b100 <
1%
#290000
0%
#292000
b1110 $
b1110 *
b1110 >
b1011 (
#295000
b110 ;
1/
b101 <
1%
#300000
0%
#305000
b101010100 ?
b1 ;
0/
b110 <
1%
#310000
0%
#315000
b10 ;
11
1.
10
b1 <
1%
#317000
b101 $
b101 *
b101 >
b1000 #
b1000 )
b1000 =
b1100 (
#320000
0%
#325000
b101000 B
b110 @
b11 ;
01
0.
00
b10 <
1%
#330000
0%
#335000
b100 ;
1-
b11 <
1%
#340000
0%
#342000
b1101 $
b1101 *
b1101 >
b1100 #
b1100 )
b1100 =
b1101 (
#345000
b101000 C
b101 ;
0-
b100 <
1%
#350000
0%
#355000
b110 ;
1/
b101 <
1%
#360000
0%
#365000
b101111100 ?
b1 ;
0/
b110 <
1%
#367000
b101 $
b101 *
b101 >
b1101 #
b1101 )
b1101 =
b1110 (
#370000
0%
#375000
b10 ;
11
1.
10
b1 <
1%
#380000
0%
#385000
b1000001 B
b111 @
b11 ;
01
0.
00
b10 <
1%
#390000
0%
#392000
b1010 $
b1010 *
b1010 >
b11 #
b11 )
b11 =
b1111 (
#395000
b100 ;
1-
b11 <
1%
#400000
0%
#405000
b1000001 C
b101 ;
0-
b100 <
1%
#410000
0%
#415000
b110 ;
1/
b101 <
1%
#417000
b10000 (
#420000
0%
#425000
b110111101 ?
b1 ;
0/
b110 <
1%
#430000
0%
#435000
b10 ;
11
1.
10
b1 <
1%
#440000
0%
#445000
b11110 B
b1000 @
b11 ;
01
0.
00
b10 <
1%
#450000
0%
#455000
b100 ;
1-
b11 <
1%
#460000
0%
#465000
b11110 C
b101 ;
0-
b100 <
1%
#470000
0%
#475000
b110 ;
1/
b101 <
1%
#480000
0%
#485000
b111011011 ?
b1 ;
0/
b110 <
1%
#490000
0%
#495000
b10 ;
11
1.
10
b1 <
1%
#500000
0%
#505000
b1001 @
b11 ;
01
0.
00
b10 <
1%
#510000
0%
#515000
b100 ;
1-
b11 <
1%
#520000
0%
#525000
b101 ;
0-
b100 <
1%
#530000
0%
#535000
b110 ;
1/
b101 <
1%
#540000
0%
#545000
b111111001 ?
b1 ;
0/
b110 <
1%
#550000
0%
#555000
b10 ;
11
1.
10
b1 <
1%
#560000
0%
#565000
b1010 @
b11 ;
01
0.
00
b10 <
1%
#570000
0%
#575000
12
b100 ;
1-
b11 <
1%
#580000
0%
#585000
b101 ;
0-
b100 <
1%
#590000
0%
#595000
b110 ;
1/
b101 <
1%
#600000
0%
#605000
b1000010111 ?
b111 ;
0/
b110 <
1%
#610000
0%
#615000
b0 ;
1,
b111 <
1%
#620000
0%
#625000
1"
b1000010111 !
b1000010111 +
b1000010111 A
b0 <
1%
