mac/mac_controlpath.v
/* 
Developed by : Vecha Sathwik
Date : 17/01/2025
Version : Beta
Rev : 1.0
Status : Working
Updates : Synchronous flow of data without pipeline
*/
`timescale 1ns / 1ps
module mac_controlpath (
    input clk,
    input rst,
    input go,
    input cmp,
    output reg load_a,
    output reg load_b,
    output reg load_m,
    output reg load_acc,
    output reg load_out,
    output reg count_enable
);

//States
parameter S0 = 3'b000;
parameter S1 = 3'b001;
parameter S2 = 3'b010;
parameter S3 = 3'b011;
parameter S4 = 3'b100;
parameter S5 = 3'b101;
parameter S6 = 3'b110;
parameter S7 = 3'b111;

//Internal Signals
reg [2:0] present_state;
reg [2:0] next_state;

//For reset Logic and Present State Logic
always @(posedge rst or posedge clk) begin
    if(rst == 1'b1) begin
        present_state = S0;
    end
    else begin
        present_state = next_state;
    end
end

//MAC Control Logic
always @(go or present_state) begin
    if(go == 1'b1 & present_state == S0) begin
        load_a = 1'b0;
        load_b = 1'b0;
        load_m = 1'b0;
        load_acc = 1'b0;
        load_out = 1'b0;
        count_enable = 1'b0;
        next_state = S1;
    end
    else begin
        case (present_state)
            S1 : begin
                load_a = 1'b1;
                load_b = 1'b1;
                load_m = 1'b0;
                load_acc = 1'b0;
                load_out = 1'b0;
                count_enable = 1'b1;
                next_state = S2;
            end

            S2 : begin
                load_a = 1'b0;
                load_b = 1'b0;
                load_m = 1'b0;
                load_acc = 1'b0;
                load_out = 1'b0;
                count_enable = 1'b0;
                next_state = S3;
            end

            S3 : begin
                load_a = 1'b0;
                load_b = 1'b0;
                load_m = 1'b1;
                load_acc = 1'b0;
                count_enable = 1'b0;
                load_out = 1'b0;
                next_state = S4;
            end

            S4 : begin
                load_a = 1'b0;
                load_b = 1'b0;
                load_m = 1'b0;
                load_acc = 1'b0;
                load_out = 1'b0;
                count_enable = 1'b0;
                next_state = S5;
            end

            S5 : begin
                load_a = 1'b0;
                load_b = 1'b0;
                load_m = 1'b0;
                load_acc = 1'b1;
                load_out = 1'b0;
                count_enable = 1'b0;
                next_state = S6;
            end

            S6 : begin
                load_a = 1'b0;
                load_b = 1'b0;
                load_m = 1'b0;
                load_acc = 1'b0;
                load_out = 1'b0;
                count_enable = 1'b0;
                next_state = (cmp == 1'b1) ? S7 : S1;
            end
            S7 : begin
                load_out = 1'b1;
                next_state = S0;
            end

            default : next_state = S0; 
        endcase
    end
end

endmodule

mac/mac_datapath.v
/* 
Developed by : Vecha Sathwik
Date : 17/01/2025
Version : Beta
Rev : 1.0
Status : Working
Updates : Synchronous flow of data without pipeline
*/

`timescale 1ns / 1ps
module mac_datapath (
    input clk,
    input rst,
    input [3:0] A,
    input [3:0] B,
    input load_a,
    input load_b,
    input load_m,
    input load_acc,
    input load_out,
    input count_enable,
    output reg [11:0] out,
    output reg cmp,
    output reg done
);

//Internal Signals
reg [11:0] Racc;
reg reset_flag;
reg [7:0] temp_min;
reg [7:0] temp_mout;
reg [3:0] count_out;

//For reset Logic
always @(posedge rst or posedge clk) begin
    if(rst == 1'b1) begin
        Racc <= 12'b0;
        done <= 1'b0;
        out <= 12'b0;
        count_out <= 4'b0;
    end
    else begin
        if(load_out == 1'b1) begin
            out <= Racc;
            done <= 1'b1;
        end
        else if (load_a == 1'b1 & load_b == 1'b1) begin
            temp_min <= A*B;            
        end
        else if(load_m == 1'b1) begin
            temp_mout <= temp_min;
        end
        else if(load_acc == 1'b1) begin
            Racc <= Racc + temp_mout;
        end
    end
end


//Logic for counter
//The below logic may not be triggered for clock instead we can provide count_enable in process sensitivity list
always @(posedge(clk)) begin
    if(count_enable == 1'b1 & count_out <= 4'b1010) begin
        count_out <= count_out + 4'b0001;
        cmp <= 1'b0;
    end
    else if(count_out == 4'b1010) begin
        cmp <= 1'b1;
    end
end


endmodule

mac/mac_topmodule.v
/* 
Developed by : Vecha Sathwik
Date : 17/01/2025
Version : Beta
Rev : 1.0
Status : Working
Updates : Synchronous flow of data without pipeline
*/
`include "mac_controlpath.v"
`include "mac_datapath.v"
`timescale 1ns / 1ps
module mac_topmodule (
    input clk,
    input rst,
    input [3:0] A,
    input [3:0] B,
    input go,
    output [11:0] out,
    output done
);

//Internal Signals
wire load_a;
wire load_b;
wire load_m;
wire load_acc;
wire load_out;
wire cmp;
wire count_enable;

//Instantiate the datapath and controlpath
mac_datapath datapath_inst1(
    .rst(rst),
    .clk(clk),
    .A(A),
    .B(B),
    .load_a(load_a),
    .load_b(load_b),
    .load_m(load_m),
    .load_acc(load_acc),
    .load_out(load_out),
    .count_enable(count_enable),
    .out(out),
    .cmp(cmp),
    .done(done)
);

mac_controlpath controlpath_inst1(
    .clk(clk),
    .rst(rst),
    .go(go),
    .cmp(cmp),
    .load_a(load_a),
    .load_b(load_b),
    .load_m(load_m),
    .load_acc(load_acc),
    .load_out(load_out),
    .count_enable(count_enable)
);
    
endmodule

mac/mac_testbench.v
/* 
Developed by : Vecha Sathwik
Date : 17/01/2025
Version : Beta
Rev : 1.0
Status : Working
Updates : Synchronous flow of data without pipeline
*/
`include "mac_topmodule.v"
`timescale 1ns / 1ps
module mac_testbench;

//Input Signals
reg clk;
reg rst;
reg go;
reg [3:0] A;
reg [3:0] B;
wire [11:0] out;
wire done;

//Instantiate the mac_topmodule
mac_topmodule mac_topmodule_inst1(
    .clk(clk),
    .rst(rst),
    .A(A),
    .B(B),
    .go(go),
    .out(out),
    .done(done)
);

//Internal Variable
integer i;

//Clock Generation
initial begin
    clk = 1'b0;
    forever begin
        #5 clk = ~clk;
    end
end

//Stimuli
initial begin
    $dumpfile("mac_testbench.vcd");
    $dumpvars;
    rst = 1'b1;
    #10;
    rst = 1'b0;
    go = 1'b1;
    #7;
    go =1'b0;
    for(i=0; i<16; i=i+1) begin
        A = $random%16;
        B = $random%16;
        #25;
    end

    #1000;
    $finish;

end
    
endmodule

mac/mac.sim/sim_1/behav/xsim/mac_testbench.vcd
$date
   Fri Jan 17 09:30:40 2025
$end
$version
  2023.1
$end
$timescale
  1ps
$end
$scope module mac_testbench $end
$var reg 1 ! clk $end
$var reg 1 " rst $end
$var reg 1 # go $end
$var reg 4 $ A [3:0] $end
$var reg 4 % B [3:0] $end
$var wire 12 & out [11:0] $end
$var wire 1 ' done $end
$var integer 32 ( i [31:0] $end
$scope module mac_topmodule_inst1 $end
$var wire 1 ) clk $end
$var wire 1 * rst $end
$var wire 4 + A [3:0] $end
$var wire 4 , B [3:0] $end
$var wire 1 - go $end
$var wire 12 & out [11:0] $end
$var wire 1 ' done $end
$var wire 1 . load_a $end
$var wire 1 / load_b $end
$var wire 1 0 load_m $end
$var wire 1 1 load_acc $end
$var wire 1 2 load_out $end
$var wire 1 3 cmp $end
$var wire 1 4 count_enable $end
$scope module datapath_inst1 $end
$var wire 1 ) clk $end
$var wire 1 * rst $end
$var wire 4 + A [3:0] $end
$var wire 4 , B [3:0] $end
$var wire 1 . load_a $end
$var wire 1 / load_b $end
$var wire 1 0 load_m $end
$var wire 1 1 load_acc $end
$var wire 1 2 load_out $end
$var wire 1 4 count_enable $end
$var reg 12 5 out [11:0] $end
$var reg 1 6 cmp $end
$var reg 1 7 done $end
$var reg 12 8 Racc [11:0] $end
$var reg 1 9 reset_flag $end
$var reg 8 : temp_min [7:0] $end
$var reg 8 ; temp_mout [7:0] $end
$var reg 4 < count_out [3:0] $end
$upscope $end
$scope module controlpath_inst1 $end
$var wire 1 ) clk $end
$var wire 1 * rst $end
$var wire 1 - go $end
$var wire 1 3 cmp $end
$var reg 1 = load_a $end
$var reg 1 > load_b $end
$var reg 1 ? load_m $end
$var reg 1 @ load_acc $end
$var reg 1 A load_out $end
$var reg 1 B count_enable $end
$var reg 3 C present_state [2:0] $end
$var reg 3 D next_state [2:0] $end
$upscope $end
$upscope $end
$upscope $end
$enddefinitions $end
#0
$dumpvars
0!
1"
x#
bx $
bx %
b0 &
0'
bx (
0)
1*
bx +
bx ,
x-
x.
x/
x0
x1
x2
x3
x4
b0 5
x6
07
b0 8
19
bx :
bx ;
b0 <
x=
x>
x?
x@
xA
xB
b0 C
b0 D
$end
#5000
1!
1)
#10000
0!
0"
1#
0)
0*
1-
b1 D
#15000
1!
1)
1.
1/
00
01
02
03
14
06
09
b1 <
1=
1>
0?
0@
0A
1B
b1 C
b10 D
#17000
0#
b100 $
b1 %
b0 (
b100 +
b1 ,
0-
b100 :
#20000
0!
0)
#25000
1!
1)
b10 C
b11 D
#30000
0!
0)
#35000
1!
1)
0.
0/
10
04
b100 ;
0=
0>
1?
0B
b11 C
b100 D
#40000
0!
0)
#45000
1!
1)
b100 C
b101 D
#47000
b1001 $
b11 %
b1 (
b1001 +
b11 ,
#50000
0!
0)
#55000
1!
1)
00
11
b100 8
0?
1@
b101 C
b110 D
#60000
0!
0)
#65000
1!
1)
b110 C
b1 D
#70000
0!
0)
#75000
1!
1)
1.
1/
01
14
b11011 :
b10 <
1=
1>
0@
1B
b1 C
b10 D
#77000
b1101 $
b1101 %
b10 (
b1101 +
b1101 ,
b10101001 :
#80000
0!
0)
#85000
1!
1)
b10 C
b11 D
#90000
0!
0)
#95000
1!
1)
0.
0/
10
04
b10101001 ;
0=
0>
1?
0B
b11 C
b100 D
#100000
0!
0)
#105000
1!
1)
b100 C
b101 D
#107000
b101 $
b10 %
b11 (
b101 +
b10 ,
#110000
0!
0)
#115000
1!
1)
00
11
b10101101 8
0?
1@
b101 C
b110 D
#120000
0!
0)
#125000
1!
1)
b110 C
b1 D
#130000
0!
0)
#135000
1!
1)
1.
1/
01
14
b1010 :
b11 <
1=
1>
0@
1B
b1 C
b10 D
#137000
b1 $
b1101 %
b100 (
b1 +
b1101 ,
b1101 :
#140000
0!
0)
#145000
1!
1)
b10 C
b11 D
#150000
0!
0)
#155000
1!
1)
0.
0/
10
04
b1101 ;
0=
0>
1?
0B
b11 C
b100 D
#160000
0!
0)
#165000
1!
1)
b100 C
b101 D
#167000
b110 $
b101 (
b110 +
#170000
0!
0)
#175000
1!
1)
00
11
b10111010 8
0?
1@
b101 C
b110 D
#180000
0!
0)
#185000
1!
1)
b110 C
b1 D
#190000
0!
0)
#195000
1!
1)
1.
1/
01
14
b1001110 :
b100 <
1=
1>
0@
1B
b1 C
b10 D
#197000
b1101 $
b1100 %
b110 (
b1101 +
b1100 ,
b10011100 :
#200000
0!
0)
#205000
1!
1)
b10 C
b11 D
#210000
0!
0)
#215000
1!
1)
0.
0/
10
04
b10011100 ;
0=
0>
1?
0B
b11 C
b100 D
#220000
0!
0)
#225000
1!
1)
b100 C
b101 D
#227000
b1001 $
b110 %
b111 (
b1001 +
b110 ,
#230000
0!
0)
#235000
1!
1)
00
11
b101010110 8
0?
1@
b101 C
b110 D
#240000
0!
0)
#245000
1!
1)
b110 C
b1 D
#250000
0!
0)
#255000
1!
1)
1.
1/
01
14
b110110 :
b101 <
1=
1>
0@
1B
b1 C
b10 D
#257000
b101 $
b1010 %
b1000 (
b101 +
b1010 ,
b110010 :
#260000
0!
0)
#265000
1!
1)
b10 C
b11 D
#270000
0!
0)
#275000
1!
1)
0.
0/
10
04
b110010 ;
0=
0>
1?
0B
b11 C
b100 D
#280000
0!
0)
#285000
1!
1)
b100 C
b101 D
#287000
b111 %
b1001 (
b111 ,
#290000
0!
0)
#295000
1!
1)
00
11
b110001000 8
0?
1@
b101 C
b110 D
#300000
0!
0)
#305000
1!
1)
b110 C
b1 D
#310000
0!
0)
#315000
1!
1)
1.
1/
01
14
b100011 :
b110 <
1=
1>
0@
1B
b1 C
b10 D
#317000
b10 $
b1111 %
b1010 (
b10 +
b1111 ,
b11110 :
#320000
0!
0)
#325000
1!
1)
b10 C
b11 D
#330000
0!
0)
#335000
1!
1)
0.
0/
10
04
b11110 ;
0=
0>
1?
0B
b11 C
b100 D
#340000
0!
0)
#345000
1!
1)
b100 C
b101 D
#347000
b1110 %
b1011 (
b1110 ,
#350000
0!
0)
#355000
1!
1)
00
11
b110100110 8
0?
1@
b101 C
b110 D
#360000
0!
0)
#365000
1!
1)
b110 C
b1 D
#370000
0!
0)
#375000
1!
1)
1.
1/
01
14
b11100 :
b111 <
1=
1>
0@
1B
b1 C
b10 D
#377000
b1000 $
b101 %
b1100 (
b1000 +
b101 ,
b101000 :
#380000
0!
0)
#385000
1!
1)
b10 C
b11 D
#390000
0!
0)
#395000
1!
1)
0.
0/
10
04
b101000 ;
0=
0>
1?
0B
b11 C
b100 D
#400000
0!
0)
#405000
1!
1)
b100 C
b101 D
#407000
b1100 $
b1101 %
b1101 (
b1100 +
b1101 ,
#410000
0!
0)
#415000
1!
1)
00
11
b111001110 8
0?
1@
b101 C
b110 D
#420000
0!
0)
#425000
1!
1)
b110 C
b1 D
#430000
0!
0)
#435000
1!
1)
1.
1/
01
14
b10011100 :
b1000 <
1=
1>
0@
1B
b1 C
b10 D
#437000
b1101 $
b101 %
b1110 (
b1101 +
b101 ,
b1000001 :
#440000
0!
0)
#445000
1!
1)
b10 C
b11 D
#450000
0!
0)
#455000
1!
1)
0.
0/
10
04
b1000001 ;
0=
0>
1?
0B
b11 C
b100 D
#460000
0!
0)
#465000
1!
1)
b100 C
b101 D
#467000
b11 $
b1010 %
b1111 (
b11 +
b1010 ,
#470000
0!
0)
#475000
1!
1)
00
11
b1000001111 8
0?
1@
b101 C
b110 D
#480000
0!
0)
#485000
1!
1)
b110 C
b1 D
#490000
0!
0)
#495000
1!
1)
1.
1/
01
14
b11110 :
b1001 <
1=
1>
0@
1B
b1 C
b10 D
#497000
b10000 (
#500000
0!
0)
#505000
1!
1)
b10 C
b11 D
#510000
0!
0)
#515000
1!
1)
0.
0/
10
04
b11110 ;
0=
0>
1?
0B
b11 C
b100 D
#520000
0!
0)
#525000
1!
1)
b100 C
b101 D
#530000
0!
0)
#535000
1!
1)
00
11
b1000101101 8
0?
1@
b101 C
b110 D
#540000
0!
0)
#545000
1!
1)
b110 C
b1 D
#550000
0!
0)
#555000
1!
1)
1.
1/
01
14
b1010 <
1=
1>
0@
1B
b1 C
b10 D
#560000
0!
0)
#565000
1!
1)
b10 C
b11 D
#570000
0!
0)
#575000
1!
1)
0.
0/
10
13
04
16
0=
0>
1?
0B
b11 C
b100 D
#580000
0!
0)
#585000
1!
1)
b100 C
b101 D
#590000
0!
0)
#595000
1!
1)
00
11
b1001001011 8
0?
1@
b101 C
b110 D
#600000
0!
0)
#605000
1!
1)
b110 C
b111 D
#610000
0!
0)
#615000
1!
b1001001011 &
1'
1)
12
b1001001011 5
17
1A
b111 C
b0 D
#620000
0!
0)
#625000
1!
1)
b0 C
