Adder/adder_controller.v
/*
Author : Vecha Sathwik
Version : 1.0
Date : 10/01/2025
Status : Working
Commit : Dev
*/

`timescale 1ns / 1ps
module adder_controller (
    input clk,rst,go,
    output reg aload,bload,cload,dload,
    output reg asel,
    output reg [1:0] bsel,
    output reg output_enable
);

//States
parameter S0 = 3'b000;
parameter S1 = 3'b001;
parameter S2 = 3'b010;
parameter S3 = 3'b011;
parameter S4 = 3'b100;
parameter S5 = 3'b101;
parameter S6 = 3'b110;

reg [2:0] present_state, next_state;

always @(posedge clk or posedge rst) begin
    if(rst == 1'b1) begin
        present_state <= S0;
    end
    else begin
        present_state <= next_state;
    end
end

always @(go or present_state) begin
    if(go == 1'b1 & present_state == S0)   begin
        next_state = S1;
        output_enable = 1'b0;        
    end
    else begin
        case (present_state)
            S1 : begin
                next_state = S2;
            end  
            S2 : begin
                aload = 1'b1;
                bload = 1'b1;
                cload = 1'b1;
                dload = 1'b1;
            end
            S3 : begin
                aload = 1'b0;
                bload = 1'b0;
                cload = 1'b0;
                dload = 1'b0;
                asel = 1'b1;
                bsel = 2'b00;
            end
            S4 : begin
                asel = 1'b0;
                bsel = 2'b01;
            end
            S5 : begin
                asel = 1'b0;
                bsel = 2'b10;
            end
            S6 : begin
                next_state = S0;
                output_enable = 1'b1;
            end
            default: begin
                next_state = S0;
            end
        endcase
    end
end 


endmodule

Adder/adder_datapath.v
`timescale 1ns/1ps;
module adder_datapath (
    input clk,
    input rst,
    input aload, bload, cload, dload,
    input asel,
    input output_enable,
    input [1:0] bsel,
    input [3:0] A, B, C, D,
    output reg [15:0] o_sum
);

reg [3:0] atemp,btemp,ctemp,dtemp;
reg [15:0] sum;

always @(posedge clk or posedge rst) begin
    if(rst) begin
        sum <= 16'b0;
    end
    else begin
        if(output_enable == 1'b1) begin
            o_sum <= sum;
        end
        else if(aload == 1'b1 & bload == 1'b1 & cload == 1'b1 & dload == 1'b1) begin
            atemp <= A;
            btemp <= B;
            ctemp <= C;
            dtemp <= D;
        end
        else if(asel == 1'b1 & bsel == 2'b00) begin
            sum <= atemp + btemp;
        end
        else if(asel == 1'b0 & bsel == 2'b01) begin
            sum <= sum + ctemp;
        end
        else if(asel == 1'b0 & bsel == 2'b10) begin
            sum <= sum + dtemp;
        end

        
    end
end
    
endmodule

Adder/adder_topmodule.v
/*
Author : Vecha Sathwik
Version : 1.0
Date : 10/01/2025
Status : Working
Commit : Dev
*/
`include "adder_controller.v"
`include "adder_datapath.v"

`timescale 1ns / 1ps
module adder_topmodule (
    input clk,
    input rst,
    input go,
    input [3:0] A,
    input [3:0] B,
    input [3:0] C,
    input [3:0] D,
    output [15:0] o_sum
);

wire asel, output_enable;
wire [1:0] bsel;
wire aload, bload, cload, dload;

adder_datapath datapath1(
    .clk(clk),
    .rst(rst),
    .aload(aload),
    .bload(bload),
    .cload(cload),
    .dload(dload),
    .asel(asel),
    .output_enable(output_enable),
    .bsel(bsel),
    .A(A),
    .B(B),
    .C(C),
    .D(D),
    .o_sum(o_sum)
);

adder_controller controller1(
    .clk(clk),
    .rst(rst),
    .go(go),
    .aload(aload),
    .bload(bload),
    .cload(cload),
    .dload(dload),
    .asel(asel),
    .bsel(bsel),
    .output_enable(output_enable)
);

endmodule

Adder/adder_testbench.v
/*
Author : Vecha Sathwik
Version : 1.0
Date : 10/01/2025
Status : Working
Commit : Dev
*/

`include "adder_topmodule.v"

`timescale 1ns / 1ps
module adder_testbench;
    reg clk, rst, go;
    reg [3:0] A, B, C, D;
    wire [15:0] o_sum;

    adder_topmodule dut(
        .clk(clk),
        .rst(rst),
        .go(go),
        .A(A),
        .B(B),
        .C(C),
        .D(D),
        .o_sum(o_sum)
    );

    //Clock Generation
    initial begin
        clk = 1'b0;
        forever #5 clk = ~clk;
    end

    //Stimuli
    initial begin
        $dumpfile("adder_testbench.vcd");
        $dumpvars;
        rst = 1'b1;
        #10 rst = 1'b0;
        go = 1'b0;
        A = 4'b0000;
        B = 4'b0010;
        C = 4'b0100;
        D = 4'b1000;
        #10 go = 1'b1;
        //$display("%d", o_sum);
        #100 $finish;
    end

endmodule

adder_Q2/adder_Q2.sim/sim_1/behav/xsim/adder_testbench.vcd
$date
   Sun Jan 12 20:21:17 2025
$end
$version
  2023.1
$end
$timescale
  1ps
$end
$scope module adder_testbench $end
$var reg 1 ! clk $end
$var reg 1 " rst $end
$var reg 1 # go $end
$var reg 4 $ A [3:0] $end
$var reg 4 % B [3:0] $end
$var reg 4 & C [3:0] $end
$var reg 4 ' D [3:0] $end
$var wire 16 ( o_sum [15:0] $end
$scope module dut $end
$var wire 1 ) clk $end
$var wire 1 * rst $end
$var wire 1 + go $end
$var wire 4 , A [3:0] $end
$var wire 4 - B [3:0] $end
$var wire 4 . C [3:0] $end
$var wire 4 / D [3:0] $end
$var wire 16 ( o_sum [15:0] $end
$var wire 1 0 asel $end
$var wire 1 1 output_enable $end
$var wire 2 2 bsel [1:0] $end
$var wire 1 3 aload $end
$var wire 1 4 bload $end
$var wire 1 5 cload $end
$var wire 1 6 dload $end
$scope module datapath1 $end
$var wire 1 ) clk $end
$var wire 1 * rst $end
$var wire 1 3 aload $end
$var wire 1 4 bload $end
$var wire 1 5 cload $end
$var wire 1 6 dload $end
$var wire 1 0 asel $end
$var wire 1 1 output_enable $end
$var wire 2 2 bsel [1:0] $end
$var wire 4 , A [3:0] $end
$var wire 4 - B [3:0] $end
$var wire 4 . C [3:0] $end
$var wire 4 / D [3:0] $end
$var reg 16 7 o_sum [15:0] $end
$var reg 4 8 atemp [3:0] $end
$var reg 4 9 btemp [3:0] $end
$var reg 4 : ctemp [3:0] $end
$var reg 4 ; dtemp [3:0] $end
$var reg 16 < sum [15:0] $end
$upscope $end
$scope module controller1 $end
$var wire 1 ) clk $end
$var wire 1 * rst $end
$var wire 1 + go $end
$var reg 1 = aload $end
$var reg 1 > bload $end
$var reg 1 ? cload $end
$var reg 1 @ dload $end
$var reg 1 A asel $end
$var reg 2 B bsel [1:0] $end
$var reg 1 C output_enable $end
$var reg 3 D present_state [2:0] $end
$var reg 3 E next_state [2:0] $end
$upscope $end
$upscope $end
$upscope $end
$enddefinitions $end
#0
$dumpvars
0!
1"
x#
bx $
bx %
bx &
bx '
bx (
0)
1*
x+
bx ,
bx -
bx .
bx /
x0
x1
bx 2
x3
x4
x5
x6
bx 7
bx 8
bx 9
bx :
bx ;
b0 <
x=
x>
x?
x@
xA
bx B
xC
b0 D
b0 E
$end
#5000
1!
1)
#10000
0!
0"
0#
b0 $
b10 %
b100 &
b1000 '
0)
0*
0+
b0 ,
b10 -
b100 .
b1000 /
#15000
1!
1)
#20000
0!
1#
0)
1+
01
0C
b1 E
#25000
1!
1)
b1 D
b10 E
#30000
0!
0)
#35000
1!
1)
13
14
15
16
1=
1>
1?
1@
b10 D
b11 E
#40000
0!
0)
#45000
1!
1)
10
b0 2
03
04
05
06
b0 8
b10 9
b100 :
b1000 ;
0=
0>
0?
0@
1A
b0 B
b11 D
b100 E
#50000
0!
0)
#55000
1!
1)
00
b1 2
b10 <
0A
b1 B
b100 D
b101 E
#60000
0!
0)
#65000
1!
1)
b10 2
b110 <
b10 B
b101 D
b110 E
#70000
0!
0)
#75000
1!
1)
11
b1110 <
1C
b110 D
b0 E
#80000
0!
0)
#85000
1!
b1110 (
1)
01
b1110 7
0C
b0 D
b1 E
#90000
0!
0)
#95000
1!
1)
b10110 <
b1 D
b10 E
#100000
0!
0)
#105000
1!
1)
13
14
15
16
b11110 <
1=
1>
1?
1@
b10 D
b11 E
#110000
0!
0)
#115000
1!
1)
10
b0 2
03
04
05
06
0=
0>
0?
0@
1A
b0 B
b11 D
b100 E
